broflow/__init__.py
broflow/action.py
broflow/action_async.py
broflow/config.py
broflow/flow.py
broflow/flow_async.py
broflow/parallel_action.py
broflow/state.py
broflow-0.1.5.dist-info/licenses/LICENSE
broflow-0.1.5.dist-info/METADATA
broflow-0.1.5.dist-info/WHEEL
broflow-0.1.5.dist-info/top_level.txt
broflow-0.1.5.dist-info/RECORD
