Metadata-Version: 2.4
Name: broflow
Version: 0.1.5
Summary: Run your workflow with lightweight library. This is how broflow flows.
Requires-Python: >=3.11
License-File: LICENSE
Requires-Dist: pyyaml>=6.0.2
Dynamic: license-file
